schema_string-0.1.0.dist-info/licenses/LICENSE
simple_schema/__init__.py
simple_schema/utilities.py
simple_schema/core/__init__.py
simple_schema/core/builders.py
simple_schema/core/fields.py
simple_schema/core/validators.py
simple_schema/examples/__init__.py
simple_schema/examples/presets.py
simple_schema/examples/recipes.py
simple_schema/integrations/__init__.py
simple_schema/integrations/json_schema.py
simple_schema/integrations/openapi.py
simple_schema/integrations/pydantic.py
simple_schema/integrations/reverse.py
simple_schema/parsing/__init__.py
simple_schema/parsing/optimizer.py
simple_schema/parsing/string_parser.py
simple_schema/parsing/syntax.py
schema_string-0.1.0.dist-info/METADATA
schema_string-0.1.0.dist-info/WHEEL
schema_string-0.1.0.dist-info/top_level.txt
schema_string-0.1.0.dist-info/RECORD
